{"2610":"81-67-218-68.rev.numericable.fr","2611":"81-67-218-68.rev.numericable.fr","2638":"81-67-218-68.rev.numericable.fr","293":"81-67-218-68.rev.numericable.fr","2650":"81-67-218-68.rev.numericable.fr","2663":"81-67-218-68.rev.numericable.fr","2675":"81-67-218-68.rev.numericable.fr","2685":"81-67-218-68.rev.numericable.fr","2696":"81-67-218-68.rev.numericable.fr","2701":"81-67-218-68.rev.numericable.fr","2704":"81-67-218-68.rev.numericable.fr","2713":"81-67-218-68.rev.numericable.fr","2715":"81-67-218-68.rev.numericable.fr","2722":"81-67-218-68.rev.numericable.fr","2733":"81-67-218-68.rev.numericable.fr","2773":"81-67-218-68.rev.numericable.fr","2776":"81-67-218-68.rev.numericable.fr","2804":"81-67-218-68.rev.numericable.fr","2862":"81-67-218-68.rev.numericable.fr","2888":"81-67-218-68.rev.numericable.fr","2895":"81-67-218-68.rev.numericable.fr","2896":"81-67-218-68.rev.numericable.fr","2909":"212-198-150-205.rev.numericable.fr","2944":"ip-115.net-82-216-32.toulouse.rev.numericable.fr","2952":"213-245-37-222.rev.numericable.fr","2964":"abo-120-81-68.mrs.modulonet.fr","2973":"213-245-37-222.rev.numericable.fr","2979":"213-245-37-222.rev.numericable.fr","3022":"but77-1-88-188-168-128.fbx.proxad.net","3037":"213-245-57-144.rev.numericable.fr","3038":"213-245-57-144.rev.numericable.fr","3047":"213-245-57-144.rev.numericable.fr","3054":"213-245-57-144.rev.numericable.fr","3062":"213-245-57-144.rev.numericable.fr","3091":"213-245-57-144.rev.numericable.fr","3100":"213-245-57-144.rev.numericable.fr","3112":"213-245-57-144.rev.numericable.fr","1447":"213-245-57-144.rev.numericable.fr","3188":"213-245-57-144.rev.numericable.fr","3191":"213-245-57-144.rev.numericable.fr","3192":"213-245-57-144.rev.numericable.fr","3213":"213-245-57-144.rev.numericable.fr","3317":"213-245-55-87.rev.numericable.fr","3329":"213-245-55-87.rev.numericable.fr","3351":"213-245-55-87.rev.numericable.fr","1373":"213-245-55-87.rev.numericable.fr","3407":"213-245-55-87.rev.numericable.fr","3469":"213-245-55-87.rev.numericable.fr","3586":"213-245-44-146.rev.numericable.fr","1054":"213-245-44-146.rev.numericable.fr","3618":"213-245-44-146.rev.numericable.fr"}